twi/__init__.py
twi/app.py
twi-0.0.5.dist-info/LICENSE
twi-0.0.5.dist-info/METADATA
twi-0.0.5.dist-info/WHEEL
twi-0.0.5.dist-info/entry_points.txt
twi-0.0.5.dist-info/top_level.txt
twi-0.0.5.dist-info/RECORD
