Metadata-Version: 2.1
Name: twi
Version: 0.0.5
Summary: do Twitter things via CLI
Home-page: http://code.averba.ch/Zev/twi
Author: Zev Averbach
Author-email: zev@averba.ch
License: MIT
License-File: LICENSE
Requires-Dist: tweepy
